knowl_apidocs/__init__.py
knowl_apidocs/apidocs.py
knowl_apidocs/exception.py
knowl_apidocs/runtime_endpoint_generation.py
knowl_apidocs/version.py
knowl_apidocs-0.2.16.36.dist-info/METADATA
knowl_apidocs-0.2.16.36.dist-info/WHEEL
knowl_apidocs-0.2.16.36.dist-info/entry_points.txt
knowl_apidocs-0.2.16.36.dist-info/top_level.txt
knowl_apidocs-0.2.16.36.dist-info/RECORD
