Metadata-Version: 2.1
Name: knowl_apidocs
Version: 0.2.16.36
Summary: Automatically generate comprehensive API documentation for your Python Django projects with **knowl-apidocs**. It's the first tool of its kind, offering a 100% automated solution to create detailed API docs without writing a single line of code.
Home-page: https://github.com/knowl-doc/APIDocs
